.version
LICENSE.txt
MANIFEST.in
README.md
setup.cfg
setup.py
saltypie/__init__.py
saltypie/exceptions.py
saltypie/salt.py
saltypie.egg-info/PKG-INFO
saltypie.egg-info/SOURCES.txt
saltypie.egg-info/dependency_links.txt
saltypie.egg-info/requires.txt
saltypie.egg-info/top_level.txt
saltypie/output/__init__.py
saltypie/output/base.py
saltypie/output/orchestration.py
saltypie/output/state.py