Metadata-Version: 2.1
Name: saltypie
Version: 0.13.0
Summary: Saltypie - salt-api wrapper and return parser
Home-page: https://gitlab.com/cathaldallan/saltypie
Author: Wilson Santos
Author-email: wilson@codeminus.org
License: MIT
Keywords: saltstack salt salt-api wrapper
Platform: UNKNOWN
Classifier: Programming Language :: Python :: 2.7
Classifier: Programming Language :: Python :: 3
